Metadata-Version: 1.0
Name: BinoGausDist
Version: 1.0
Summary: Gaussian and Binomial distributions
Home-page: UNKNOWN
Author: Ajitesh Gupta
Author-email: ajiteshgupta13@gmail.com
License: UNKNOWN
Platform: UNKNOWN
